code.py
examples/demo1.py
examples/demo2.py
examples/demo3.py
examples/demo4.py
luminaria/__init__.py
luminaria/animations.py
luminaria/colors.py
luminaria/models.py
luminaria/utils.py
luminaria/renderer/__init__.py
luminaria/renderer/circuitpython_neopixel_renderer.py
luminaria/renderer/wx_renderer.py
other/__init__.py
other/main_host.py
luminaria-0.5.dist-info/LICENSE
luminaria-0.5.dist-info/METADATA
luminaria-0.5.dist-info/WHEEL
luminaria-0.5.dist-info/top_level.txt
luminaria-0.5.dist-info/RECORD
