Metadata-Version: 2.1
Name: luminaria
Version: 0.5
Summary: Animate pixels and render on Neopixel strips or other outputs
Author-email: John Petrangelo <john@petrangelo.org>
License: MIT License
Keywords: led,neopixel
Classifier: Development Status :: 2 - Pre-Alpha
Requires-Python: >=3.9
License-File: LICENSE
Requires-Dist: adafruit-circuitpython-httpserver
Requires-Dist: adafruit-circuitpython-neopixel
Requires-Dist: circuitpython-stubs
Requires-Dist: wxPython
